README.md
setup.cfg
setup.py
distribu55/Binomialdistribution.py
distribu55/Gaussiandistribution.py
distribu55/Generaldistribution.py
distribu55/__init__.py
distribu55.egg-info/PKG-INFO
distribu55.egg-info/SOURCES.txt
distribu55.egg-info/dependency_links.txt
distribu55.egg-info/not-zip-safe
distribu55.egg-info/top_level.txt